poetry_dotenv_plugin/__init__.py
poetry_dotenv_plugin/dotenv_plugin.py
poetry_dotenv_plugin-0.1.0.dist-info/entry_points.txt
poetry_dotenv_plugin-0.1.0.dist-info/LICENSE
poetry_dotenv_plugin-0.1.0.dist-info/WHEEL
poetry_dotenv_plugin-0.1.0.dist-info/METADATA
poetry_dotenv_plugin-0.1.0.dist-info/RECORD
