Metadata-Version: 2.1
Name: poetry-dotenv-plugin
Version: 0.1.0
Summary: A Poetry plugin to automatically load environment variables from .env files
Home-page: https://github.com/mpeteuil/poetry-dotenv-plugin
License: MIT
Keywords: poetry,poetry-plugin,plugin,dotenv
Author: Michael Peteuil
Author-email: michael.peteuil@gmail.com
Requires-Python: >=3.7,<4
Classifier: License :: OSI Approved :: MIT License
Classifier: Programming Language :: Python :: 3
Classifier: Programming Language :: Python :: 3.7
Classifier: Programming Language :: Python :: 3.8
Classifier: Programming Language :: Python :: 3.9
Classifier: Programming Language :: Python :: 3.10
Classifier: Topic :: Software Development
Classifier: Topic :: System :: Systems Administration
Classifier: Topic :: Utilities
Requires-Dist: poetry (>=1.2.0a1)
Requires-Dist: python-dotenv (>=0.10.0)
Project-URL: Repository, https://github.com/mpeteuil/poetry-dotenv-plugin
